{
  "count": 2,
  "value": [
    {
      "id": "pkg-nuget-1",
      "name": "Contoso.Core",
      "protocolType": "NuGet",
      "versions": [
        {
          "id": "v1",
          "version": "1.0.0",
          "isLatest": false
        },
        {
          "id": "v2",
          "version": "1.1.0",
          "isLatest": true
        }
      ]
    },
    {
      "id": "pkg-npm-1",
      "name": "contoso-ui",
      "protocolType": "Npm",
      "versions": [
        {
          "id": "v1",
          "version": "2.0.0",
          "isLatest": true
        }
      ]
    }
  ]
}